memory_monitor/__init__.py
memory_monitor/etc/nbextension.json
memory_monitor/etc/serverextension.json
memory_monitor/static/README.md
memory_monitor/static/main.css
memory_monitor/static/main.html
memory_monitor/static/main.js
memory_monitor/static/memory_monitor.yaml
memory_monitor/static/utils.js
memory_monitor-0.1.11.data/data/etc/jupyter/jupyter_notebook_config.d/serverextension.json
memory_monitor-0.1.11.data/data/etc/jupyter/nbconfig/notebook.d/nbextension.json
memory_monitor-0.1.11.data/data/share/jupyter/nbextensions/memory_monitor/README.md
memory_monitor-0.1.11.data/data/share/jupyter/nbextensions/memory_monitor/main.css
memory_monitor-0.1.11.data/data/share/jupyter/nbextensions/memory_monitor/main.html
memory_monitor-0.1.11.data/data/share/jupyter/nbextensions/memory_monitor/main.js
memory_monitor-0.1.11.data/data/share/jupyter/nbextensions/memory_monitor/memory_monitor.yaml
memory_monitor-0.1.11.data/data/share/jupyter/nbextensions/memory_monitor/utils.js
memory_monitor-0.1.11.dist-info/LICENSE
memory_monitor-0.1.11.dist-info/METADATA
memory_monitor-0.1.11.dist-info/WHEEL
memory_monitor-0.1.11.dist-info/top_level.txt
memory_monitor-0.1.11.dist-info/RECORD
