Metadata-Version: 2.1
Name: memory-monitor
Version: 0.1.11
Summary: Jupyter Extension that monitors the memory consumption, and shuts down the kernel
Home-page: https://github.com/steelersd/memory_monitor
License: MIT
Keywords: Jupyter,Notebook,Extension
Platform: UNKNOWN
Requires-Python: >=3.6
